kuuk/__init__.py
kuuk/api/__init__.py
kuuk/api/root.py
kuuk/api/routes.py
kuuk/api/serializers/__init__.py
kuuk/api/serializers/register.py
kuuk/cli/__init__.py
kuuk/cli/main.py
kuuk/client/__init__.py
kuuk/client/entities.py
kuuk/entities/__init__.py
kuuk/entities/graph.py
kuuk/entities/link.py
kuuk/entities/project.py
kuuk/entities/stage.py
kuuk/entities/models/__init__.py
kuuk/entities/models/base.py
kuuk/entities/models/registrable.py
kuuk/server/__init__.py
kuuk/server/configs.py
kuuk/server/database.py
kuuk/server/server_app.py
kuuk/server/session.py
kuuk-0.1.4.dist-info/licenses/LICENSE
kuuk-0.1.4.dist-info/METADATA
kuuk-0.1.4.dist-info/WHEEL
kuuk-0.1.4.dist-info/entry_points.txt
kuuk-0.1.4.dist-info/top_level.txt
kuuk-0.1.4.dist-info/RECORD
