Metadata-Version: 2.4
Name: kuuk
Version: 0.1.4
Summary: Add your description here
Author: pablo-desperados
License-Expression: Apache-2.0
Project-URL: Homepage, https://github.com/pablo-desperados/kuuk
Requires-Python: >=3.12
License-File: LICENSE
Requires-Dist: starlette>=0.50.0
Requires-Dist: uvicorn>=0.38.0
Requires-Dist: sqlalchemy>=2.0.0
Requires-Dist: pydantic>=2.12.5
Dynamic: license-file
